planarpy/__init__.py
planarpy/dom.py
planarpy/expr.py
planarpy/mesh.py
planarpy/planarpy.cp310-win_amd64.pyd
planarpy/seq.py
planarpy-0.0.8.data/data/README/README.md
planarpy-0.0.8.data/data/licenses/APACHE2
planarpy-0.0.8.data/data/licenses/MIT
planarpy-0.0.8.dist-info/LICENSE
planarpy-0.0.8.dist-info/METADATA
planarpy-0.0.8.dist-info/WHEEL
planarpy-0.0.8.dist-info/top_level.txt
planarpy-0.0.8.dist-info/RECORD
